pisp.py
point_in_sph_poly-1.0.dist-info/licenses/LICENSE
point_in_sph_poly-1.0.dist-info/METADATA
point_in_sph_poly-1.0.dist-info/WHEEL
point_in_sph_poly-1.0.dist-info/top_level.txt
point_in_sph_poly-1.0.dist-info/RECORD
